Metadata-Version: 2.1
Name: django-pwa-webpush
Version: 1.1.3
Summary: A conglomeration of django-pwa and django-webpush.
Home-page: https://www.github.com/avryhof/django-pwa-webpush
Author: Amos Vryhof
Author-email: amos@vryhofresearch.com
License: GNU Public License
Classifier: Environment :: Web Environment
Classifier: Framework :: Django
Classifier: Intended Audience :: Developers
Classifier: License :: OSI Approved :: GNU General Public License v3 (GPLv3)
Classifier: Operating System :: OS Independent
Classifier: Programming Language :: Python
Classifier: Programming Language :: Python :: 3
Classifier: Topic :: Internet :: WWW/HTTP
Classifier: Topic :: Internet :: WWW/HTTP :: Dynamic Content
License-File: LICENSE
Requires-Dist: pywebpush (>=1.6.0)
